testimonials/__init__.py
testimonials/admin.py
testimonials/apps.py
testimonials/static/css/testimonials/bethany_ds.css
testimonials/static/css/testimonials/medilab_ds.css
testimonials/static/css/testimonials/mentor_ds.css
testimonials/templates/testimonials/_common.html
testimonials/templates/testimonials/bethany_ds.html
testimonials/templates/testimonials/medilab_ds.html
testimonials/templates/testimonials/mentor_ds.html
testimonials/templatetags/__init__.py
testimonials/templatetags/testimonials_tags.py
django_testimonials_ds-1.1.1.dist-info/LICENSE
django_testimonials_ds-1.1.1.dist-info/METADATA
django_testimonials_ds-1.1.1.dist-info/WHEEL
django_testimonials_ds-1.1.1.dist-info/top_level.txt
django_testimonials_ds-1.1.1.dist-info/RECORD
